.gitignore
.hgignore
README.rst
common_mimetypes.py
setup.py
common_mimetypes.egg-info/PKG-INFO
common_mimetypes.egg-info/SOURCES.txt
common_mimetypes.egg-info/dependency_links.txt
common_mimetypes.egg-info/namespace_packages.txt
common_mimetypes.egg-info/top_level.txt
common_mimetypes.egg-info/zip-safe