Metadata-Version: 1.0
Name: common-mimetypes
Version: 0.1rc1
Summary: Common MIME types
Home-page: https://github.com/iki/common-mimetypes
Author: Jan Killian
Author-email: jan.killian@gmail.com
License: BSD
Keywords: MIME,type,mimetype
Platform: any
Classifier: Development Status :: 4 - Beta
Classifier: Intended Audience :: Developers
Classifier: License :: OSI Approved :: BSD License
Classifier: Operating System :: OS Independent
Classifier: Programming Language :: Python
Classifier: Topic :: Internet :: WWW/HTTP :: Dynamic Content :: CGI Tools/Libraries
Classifier: Topic :: Software Development :: Libraries :: Python Modules
